snowglobes_data/__init__.py
snowglobes_data/detector_configurations.dat
snowglobes_data/channels/__init__.py
snowglobes_data/channels/channels_argon.dat
snowglobes_data/channels/channels_argon_400bins.dat
snowglobes_data/channels/channels_argon_ah.dat
snowglobes_data/channels/channels_argon_ah_he.dat
snowglobes_data/channels/channels_argon_coh.dat
snowglobes_data/channels/channels_argon_he.dat
snowglobes_data/channels/channels_argon_klmv.dat
snowglobes_data/channels/channels_argon_marley1.dat
snowglobes_data/channels/channels_argon_marley2.dat
snowglobes_data/channels/channels_germanium_coh.dat
snowglobes_data/channels/channels_heavywater.dat
snowglobes_data/channels/channels_lead.dat
snowglobes_data/channels/channels_nova_soup.dat
snowglobes_data/channels/channels_scint.dat
snowglobes_data/channels/channels_water.dat
snowglobes_data/channels/channels_water_he.dat
snowglobes_data/channels/channels_xenon_coh.dat
snowglobes_data/effic/ar40kt/effic_nc_ah_nue_Ar40_ar40kt.dat
snowglobes_data/effic/ar40kt/effic_nc_ah_nuebar_Ar40_ar40kt.dat
snowglobes_data/effic/ar40kt/effic_nc_ah_numu_Ar40_ar40kt.dat
snowglobes_data/effic/ar40kt/effic_nc_ah_numubar_Ar40_ar40kt.dat
snowglobes_data/effic/ar40kt/effic_nc_ah_nutau_Ar40_ar40kt.dat
snowglobes_data/effic/ar40kt/effic_nc_ah_nutaubar_Ar40_ar40kt.dat
snowglobes_data/effic/ar40kt/effic_nc_nue_Ar40_ar40kt.dat
snowglobes_data/effic/ar40kt/effic_nc_nuebar_Ar40_ar40kt.dat
snowglobes_data/effic/ar40kt/effic_nc_numu_Ar40_ar40kt.dat
snowglobes_data/effic/ar40kt/effic_nc_numubar_Ar40_ar40kt.dat
snowglobes_data/effic/ar40kt/effic_nc_nutau_Ar40_ar40kt.dat
snowglobes_data/effic/ar40kt/effic_nc_nutaubar_Ar40_ar40kt.dat
snowglobes_data/effic/ar40kt/effic_nue_Ar40_ar40kt.dat
snowglobes_data/effic/ar40kt/effic_nue_Ar40_klmv_ar40kt.dat
snowglobes_data/effic/ar40kt/effic_nue_Ar40_marley1_ar40kt.dat
snowglobes_data/effic/ar40kt/effic_nue_Ar40_marley2_ar40kt.dat
snowglobes_data/effic/ar40kt/effic_nue_e_ar40kt.dat
snowglobes_data-1.3.1.dist-info/METADATA
snowglobes_data-1.3.1.dist-info/WHEEL
snowglobes_data-1.3.1.dist-info/top_level.txt
snowglobes_data-1.3.1.dist-info/RECORD
