Metadata-Version: 2.1
Name: snowglobes-data
Version: 1.3.1
Summary: Data files included as part of SNOwGLoBES
Author: SNOwGLoBES Contributors
Project-URL: Homepage, https://github.com/SNOwGLoBES/snowglobes
Project-URL: Bug Tracker, https://github.com/SNOwGLoBES/snowglobes/issues
Classifier: Programming Language :: Python :: 3
Classifier: License :: OSI Approved :: GNU General Public License v2 (GPLv2)
Classifier: Operating System :: OS Independent
Classifier: Topic :: Scientific/Engineering :: Physics
Requires-Python: >=3.7
